{"nodes": [{"id": "a4a7a9cd_arduino_uno", "label": "Arduino Uno", "file_type": "image", "source_file": "images/a4a7a9cd-806c-4b72-8d80-14e08ae2ccf5.JPG", "source_location": null, "source_url": null, "captured_at": null, "author": null, "contributor": null}, {"id": "a4a7a9cd_motor_driver_module", "label": "Motor Driver Module", "file_type": "image", "source_file": "images/a4a7a9cd-806c-4b72-8d80-14e08ae2ccf5.JPG", "source_location": null, "source_url": null, "captured_at": null, "author": null, "contributor": null}, {"id": "a4a7a9cd_battery_pack", "label": "Battery Pack", "file_type": "image", "source_file": "images/a4a7a9cd-806c-4b72-8d80-14e08ae2ccf5.JPG", "source_location": null, "source_url": null, "captured_at": null, "author": null, "contributor": null}, {"id": "a4a7a9cd_robot_chassis", "label": "Wheeled Robot Chassis", "file_type": "image", "source_file": "images/a4a7a9cd-806c-4b72-8d80-14e08ae2ccf5.JPG", "source_location": null, "source_url": null, "captured_at": null, "author": null, "contributor": null}, {"id": "a4a7a9cd_dc_gear_motors", "label": "DC Gear Motors", "file_type": "image", "source_file": "images/a4a7a9cd-806c-4b72-8d80-14e08ae2ccf5.JPG", "source_location": null, "source_url": null, "captured_at": null, "author": null, "contributor": null}, {"id": "a4a7a9cd_wiring_harness", "label": "Wiring Harness", "file_type": "image", "source_file": "images/a4a7a9cd-806c-4b72-8d80-14e08ae2ccf5.JPG", "source_location": null, "source_url": null, "captured_at": null, "author": null, "contributor": null}], "edges": [{"source": "a4a7a9cd_arduino_uno", "target": "a4a7a9cd_motor_driver_module", "relation": "shares_data_with", "confidence": "INFERRED", "confidence_score": 0.91, "source_file": "images/a4a7a9cd-806c-4b72-8d80-14e08ae2ccf5.JPG", "source_location": null, "weight": 0.91}, {"source": "a4a7a9cd_battery_pack", "target": "a4a7a9cd_robot_chassis", "relation": "conceptually_related_to", "confidence": "EXTRACTED", "confidence_score": 0.98, "source_file": "images/a4a7a9cd-806c-4b72-8d80-14e08ae2ccf5.JPG", "source_location": null, "weight": 0.98}, {"source": "a4a7a9cd_motor_driver_module", "target": "a4a7a9cd_dc_gear_motors", "relation": "conceptually_related_to", "confidence": "INFERRED", "confidence_score": 0.87, "source_file": "images/a4a7a9cd-806c-4b72-8d80-14e08ae2ccf5.JPG", "source_location": null, "weight": 0.87}, {"source": "a4a7a9cd_wiring_harness", "target": "a4a7a9cd_arduino_uno", "relation": "references", "confidence": "EXTRACTED", "confidence_score": 0.93, "source_file": "images/a4a7a9cd-806c-4b72-8d80-14e08ae2ccf5.JPG", "source_location": null, "weight": 0.93}, {"source": "a4a7a9cd_wiring_harness", "target": "a4a7a9cd_motor_driver_module", "relation": "references", "confidence": "EXTRACTED", "confidence_score": 0.93, "source_file": "images/a4a7a9cd-806c-4b72-8d80-14e08ae2ccf5.JPG", "source_location": null, "weight": 0.93}, {"source": "a4a7a9cd_wiring_harness", "target": "a4a7a9cd_battery_pack", "relation": "references", "confidence": "EXTRACTED", "confidence_score": 0.88, "source_file": "images/a4a7a9cd-806c-4b72-8d80-14e08ae2ccf5.JPG", "source_location": null, "weight": 0.88}], "hyperedges": [{"id": "robot_drive_assembly", "label": "Robot Drive Assembly", "nodes": ["a4a7a9cd_robot_chassis", "a4a7a9cd_dc_gear_motors", "a4a7a9cd_motor_driver_module", "a4a7a9cd_arduino_uno", "a4a7a9cd_battery_pack", "a4a7a9cd_wiring_harness"], "relation": "form", "confidence": "EXTRACTED", "confidence_score": 0.96, "source_file": "images/a4a7a9cd-806c-4b72-8d80-14e08ae2ccf5.JPG"}]}